{"cameraMode":{"drawMode":0,"name":"Shaded","section":"Shading Mode"},"sceneLighting":true,"audioPlay":false,"sceneViewState":{"m_AlwaysRefresh":false,"showFog":true,"showSkybox":true,"showFlares":true,"showImageEffects":true,"showParticleSystems":true,"showVisualEffectGraphs":true,"m_FxEnabled":true},"in2DMode":false,"pivot":{"x":1.263142704963684,"y":1.4243121147155762,"z":-3.074403762817383},"rotation":{"x":0.35373303294181826,"y":-0.27818477153778078,"z":0.11103201657533646,"w":0.8861066102981567},"size":5.3781328201293949,"orthographic":false}